{
	"love": [
		"деньги",
		"чй",
		"котики",
		"Компуктр сайнс",
		"лоли",
		"лоли",
		"лоли",
		"лоли",
		"лоли",
		"лоли",
		"лоли"
	],
	"projects": {
		"Моя первая серьезная попытка в веб": "https://github.com/dokieki/my-styles",
		"Сайт с анекдотами": "https://github.com/dokieki/anekdots",
		"Этот сайт": "https://github.com/dokieki/website123"
	},
	"music": [
		"Negative XP",
		"The Drums",
		"Убей меня, Эйс!",
		"Перемотка",
		"Деревянные киты",
		"Автоспорт",
		"Источник",
		"Krovostok",
		"Мой друг магнитафон",
		"Электрофорез",
		"Сплин",
		"Аквариум",
		"my dead girlfriend",
		"Найк борзов",
		"Кино",
		"Sum 41",
		"ssshhhiiittt!",
		"System of a down",
		"Ozzy Osbourne",
		"Увула",
		"Kashtanka",
		"ДДТ",
		"S3RL",
		"второй этаж поражает",
		"Goldfinger",
		"The offspring",
		"Пикник",
		"Capstan",
		"Verbludes",
		"Ноль",
		"Галантерея",
		"Pompeya",
		"Motorama",
		"пенделюм",
		"вечеринка ножей"
	],
	"contacts": {
		"Discord": "https://discord.gg/JQvTN4t",
		"Telegram": "https://t.me/joinchat/l7ydozB0ZcUzNTNi",
		"Github": "https://github.com/dokieki",
		"VK": "https://vk.com/coolpenis69"
	}
}
